lqtmoment/__init__.py
lqtmoment/api.py
lqtmoment/catalog_builder.py
lqtmoment/config.py
lqtmoment/fitting_spectral.py
lqtmoment/lqt_analysis.py
lqtmoment/main.py
lqtmoment/plotting.py
lqtmoment/processing.py
lqtmoment/refraction.py
lqtmoment/utils.py
lqtmoment/data/__init__.py
lqtmoment/data/config.ini
lqtmoment/data/velocity_model.json
lqtmoment-0.2.1.dist-info/licenses/LICENSE
lqtmoment-0.2.1.dist-info/METADATA
lqtmoment-0.2.1.dist-info/WHEEL
lqtmoment-0.2.1.dist-info/entry_points.txt
lqtmoment-0.2.1.dist-info/top_level.txt
lqtmoment-0.2.1.dist-info/RECORD
