Metadata-Version: 2.4
Name: lqtmoment
Version: 0.2.1
Summary: Compute seismic moment in LQT systems with advanced spectral fitting
Author-email: Arham Zakki Edelo <edelo.arham@gmail.com>
License: MIT License
Project-URL: Homepage, https://github.com/bgjx/lqt-moment-magnitude
Project-URL: Repository, https://github.com/bgjx/lqt-moment-magnitude
Project-URL: Documentation, https://bgjx.io/lqtmoment
Project-URL: BugTracker, https://github.com/bgjx/lqt-moment-magnitude/issues
Keywords: Seismology,Moment Magnitude,Spectral Fitting,LQT Component,Earthquake,Geophysics
Classifier: Programming Language :: Python :: 3.9
Classifier: Programming Language :: Python :: 3.10
Classifier: Programming Language :: Python :: 3.11
Classifier: Programming Language :: Python :: 3.12
Classifier: License :: OSI Approved :: MIT License
Classifier: Operating System :: OS Independent
Classifier: Topic :: Scientific/Engineering :: Physics
Classifier: Intended Audience :: Science/Research
Classifier: Development Status :: 4 - Beta
Classifier: Natural Language :: English
Requires-Python: >=3.9
License-File: LICENSE
Requires-Dist: numpy<2.0,>=1.21.0
Requires-Dist: pandas>=1.5.0
Requires-Dist: matplotlib>=3.5.0
Requires-Dist: scipy>=1.5.0
Requires-Dist: scikit-optimize>=0.10.0
Requires-Dist: obspy>=1.3.0
Requires-Dist: tqdm>=4.60.0
Requires-Dist: configparser>=5.0.0
Requires-Dist: openpyxl>=3.0.0
Requires-Dist: plotly>=5.20.0
Provides-Extra: tests
Requires-Dist: pytest>=8.0.0; extra == "tests"
Dynamic: license-file
